LICENSE
README.md
setup.py
paddl/__init__.py
paddl/__main__.py
paddl/models.py
paddl.egg-info/PKG-INFO
paddl.egg-info/SOURCES.txt
paddl.egg-info/dependency_links.txt
paddl.egg-info/top_level.txt
paddl/csv/__init__.py
paddl/csv/__main__.py
paddl/docs/__init__.py
paddl/docs/plantuml/__init__.py
paddl/extract/__init__.py
paddl/extract/__main__.py
paddl/langs/__init__.py
paddl/langs/mysql/__init__.py
paddl/langs/mysql/definitions.py
paddl/langs/mysql/keywords.py
paddl/size/__init__.py
test/test_erd.py
test/test_overdraft.py