Metadata-Version: 2.1
Name: paddl
Version: 0.3.0
Summary: Parse Any DDL
Home-page: http://github.com/trevorgrayson/paddl
Author: trevor grayson
Author-email: trevor@dave.com
License: MIT
Classifier: License :: OSI Approved :: MIT License
Classifier: Programming Language :: Python
Classifier: Topic :: Software Development :: Libraries
Classifier: Topic :: System :: Monitoring
Classifier: Topic :: System :: Logging
License-File: LICENSE
